dojo_email/__init__.py
dojo_email/source.py
dojo_email-0.0.5.dist-info/DESCRIPTION.rst
dojo_email-0.0.5.dist-info/METADATA
dojo_email-0.0.5.dist-info/RECORD
dojo_email-0.0.5.dist-info/WHEEL
dojo_email-0.0.5.dist-info/metadata.json
dojo_email-0.0.5.dist-info/top_level.txt
