Metadata-Version: 2.0
Name: dojo-email
Version: 0.0.5
Summary: Dojo email drop source adapter
Home-page: https://dojo.dataup.me/
Author: Data Up
Author-email: dojo@dataup.me
License: UNKNOWN
Platform: UNKNOWN
Requires-Dist: dojo
